cli/__init__.py
cli/django.py
cli/pa.py
cli/path.py
cli/schedule.py
cli/students.py
cli/webapp.py
cli/website.py
pythonanywhere/__init__.py
pythonanywhere/django_project.py
pythonanywhere/django_project.pyi
pythonanywhere/exceptions.py
pythonanywhere/exceptions.pyi
pythonanywhere/files.py
pythonanywhere/files.pyi
pythonanywhere/launch_bash_in_virtualenv.py
pythonanywhere/project.py
pythonanywhere/project.pyi
pythonanywhere/scripts_commons.py
pythonanywhere/scripts_commons.pyi
pythonanywhere/students.py
pythonanywhere/students.pyi
pythonanywhere/task.py
pythonanywhere/task.pyi
pythonanywhere/utils.py
pythonanywhere/utils.pyi
pythonanywhere/virtualenvs.py
pythonanywhere/virtualenvs.pyi
pythonanywhere/wsgi_file_template.py
pythonanywhere-0.18.0.data/scripts/pa_autoconfigure_django.py
pythonanywhere-0.18.0.data/scripts/pa_create_scheduled_task.py
pythonanywhere-0.18.0.data/scripts/pa_create_webapp_with_virtualenv.py
pythonanywhere-0.18.0.data/scripts/pa_delete_scheduled_task.py
pythonanywhere-0.18.0.data/scripts/pa_delete_webapp_logs.py
pythonanywhere-0.18.0.data/scripts/pa_get_scheduled_task_specs.py
pythonanywhere-0.18.0.data/scripts/pa_get_scheduled_tasks_list.py
pythonanywhere-0.18.0.data/scripts/pa_install_webapp_letsencrypt_ssl.py
pythonanywhere-0.18.0.data/scripts/pa_install_webapp_ssl.py
pythonanywhere-0.18.0.data/scripts/pa_reload_webapp.py
pythonanywhere-0.18.0.data/scripts/pa_start_django_webapp_with_virtualenv.py
pythonanywhere-0.18.0.data/scripts/pa_update_scheduled_task.py
pythonanywhere-0.18.0.dist-info/LICENSE
pythonanywhere-0.18.0.dist-info/METADATA
pythonanywhere-0.18.0.dist-info/WHEEL
pythonanywhere-0.18.0.dist-info/entry_points.txt
pythonanywhere-0.18.0.dist-info/top_level.txt
pythonanywhere-0.18.0.dist-info/RECORD
