Metadata-Version: 2.2
Name: pythonanywhere
Version: 0.18.0
Summary: PythonAnywhere helper tools for users
Home-page: https://github.com/pythonanywhere/helper_scripts/
Author: PythonAnywhere LLP
Author-email: developers@pythonanywhere.com
License: MIT
Keywords: pythonanywhere api cloud web hosting
Classifier: Development Status :: 3 - Alpha
Classifier: Intended Audience :: Developers
Classifier: Topic :: Software Development :: Libraries
Classifier: License :: OSI Approved :: MIT License
Classifier: Programming Language :: Python :: 3.13
Classifier: Programming Language :: Python :: 3.12
Classifier: Programming Language :: Python :: 3.11
Classifier: Programming Language :: Python :: 3.10
Requires-Python: >=3.10
License-File: LICENSE
Requires-Dist: docopt
Requires-Dist: packaging
Requires-Dist: python-dateutil
Requires-Dist: pythonanywhere_core==0.2.9
Requires-Dist: requests
Requires-Dist: schema
Requires-Dist: snakesay==0.10.4
Requires-Dist: tabulate
Requires-Dist: typer
Dynamic: author
Dynamic: author-email
Dynamic: classifier
Dynamic: description
Dynamic: description-content-type
Dynamic: home-page
Dynamic: keywords
Dynamic: license
Dynamic: requires-dist
Dynamic: requires-python
Dynamic: summary
